bytecode/__init__.py
bytecode/bytecode.py
bytecode/cfg.py
bytecode/concrete.py
bytecode/effects.py
bytecode/flags.py
bytecode/instr.py
bytecode/peephole_opt.py
tests/__init__.py
tests/test_bytecode.py
tests/test_cfg.py
tests/test_code.py
tests/test_concrete.py
tests/test_flags.py
tests/test_instr.py
tests/test_misc.py
tests/test_peephole_opt.py
dead_bytecode-0.2.0.dist-info/METADATA
dead_bytecode-0.2.0.dist-info/WHEEL
dead_bytecode-0.2.0.dist-info/top_level.txt
dead_bytecode-0.2.0.dist-info/RECORD
