Metadata-Version: 2.1
Name: dead-bytecode
Version: 0.2.0
Summary: Backport of bytecode to Python 2
Home-page: https://github.com/p403n1x87/dead-bytecode
Author: Gabriele N. Tornetta
Author-email: phoenix1987@gmail.com
License: UNKNOWN
Project-URL: Source, https://github.com/p403n1x87/dead-bytecode/
Project-URL: Bug Reports, https://github.com/p403n1x87/dead-bytecode/issues
Platform: UNKNOWN
Classifier: Development Status :: 3 - Alpha
Classifier: Intended Audience :: Developers
Classifier: License :: OSI Approved :: MIT License
Classifier: Programming Language :: Python :: 2.7
Requires-Python: >=2.7, <3
Requires-Dist: aenum (>=2.0)
Requires-Dist: unittest2
Provides-Extra: test
Requires-Dist: coverage ; extra == 'test'
Requires-Dist: pytest ; extra == 'test'
Requires-Dist: pytest-cov ; extra == 'test'
